odoo/addons/test_ssi_duration_mixin/README.rst
odoo/addons/test_ssi_duration_mixin/__init__.py
odoo/addons/test_ssi_duration_mixin/__manifest__.py
odoo/addons/test_ssi_duration_mixin/models/__init__.py
odoo/addons/test_ssi_duration_mixin/models/test_master_data_date_duration.py
odoo/addons/test_ssi_duration_mixin/models/test_transaction_date_duration.py
odoo/addons/test_ssi_duration_mixin/security/ir.model.access.csv
odoo/addons/test_ssi_duration_mixin/static/description/icon.png
odoo/addons/test_ssi_duration_mixin/views/test_master_data_date_duration_views.xml
odoo/addons/test_ssi_duration_mixin/views/test_transaction_date_duration_views.xml
odoo14_addon_test_ssi_duration_mixin-14.0.1.1.0.dist-info/METADATA
odoo14_addon_test_ssi_duration_mixin-14.0.1.1.0.dist-info/WHEEL
odoo14_addon_test_ssi_duration_mixin-14.0.1.1.0.dist-info/top_level.txt
odoo14_addon_test_ssi_duration_mixin-14.0.1.1.0.dist-info/RECORD
